epss_api.py
epss_mcp.py
nvd_api.py
iflow_mcp_epss_mcp-0.1.0.dist-info/licenses/LICENSE
iflow_mcp_epss_mcp-0.1.0.dist-info/METADATA
iflow_mcp_epss_mcp-0.1.0.dist-info/WHEEL
iflow_mcp_epss_mcp-0.1.0.dist-info/entry_points.txt
iflow_mcp_epss_mcp-0.1.0.dist-info/top_level.txt
iflow_mcp_epss_mcp-0.1.0.dist-info/RECORD
