Metadata-Version: 2.4
Name: iflow-mcp_EPSS-MCP
Version: 0.1.0
Summary: EPSS MCP Server - Retrieve CVE details from NVD API and EPSS scores
Requires-Python: >=3.10
License-File: LICENSE
Requires-Dist: httpx
Requires-Dist: fastapi
Requires-Dist: uvicorn
Requires-Dist: pydantic
Requires-Dist: mcp[cli]
Dynamic: license-file
